MANIFEST.in
README.rst
setup.py
tw2/__init__.py
tw2.etc.egg-info/PKG-INFO
tw2.etc.egg-info/SOURCES.txt
tw2.etc.egg-info/dependency_links.txt
tw2.etc.egg-info/entry_points.txt
tw2.etc.egg-info/namespace_packages.txt
tw2.etc.egg-info/not-zip-safe
tw2.etc.egg-info/requires.txt
tw2.etc.egg-info/top_level.txt
tw2/etc/__init__.py
tw2/etc/samples.py
tw2/etc/widgets.py
tw2/etc/templates/__init__.py
tw2/etc/templates/iframe.html
tw2/etc/templates/iframe.mak