Metadata-Version: 1.1
Name: tw2.etc
Version: 2.1.0
Summary: Random extra widgets for ToscaWidgets 2.
Home-page: https://github.com/toscawidgets/tw2.etc
Author: Ralph Bean
Author-email: rbean@redhat.com
License: UNKNOWN
Keywords: toscawidgets.widgets
Platform: UNKNOWN
Classifier: Development Status :: 3 - Alpha
Classifier: Environment :: Web Environment
Classifier: Environment :: Web Environment :: ToscaWidgets
Classifier: Topic :: Software Development :: Libraries :: Python Modules
Classifier: Topic :: Software Development :: Widget Sets
Classifier: Intended Audience :: Developers
Classifier: Operating System :: OS Independent
Classifier: Programming Language :: Python
